<layer>
  <name>bak_rub1_songkha_v1_pp</name>
  <id>LayerInfoImpl-19c07171:1971a26b73f:-7eed</id>
  <type>VECTOR</type>
  <defaultStyle>
    <id>StyleInfoImpl-78eb30e8:1973939a8f6:3a37</id>
  </defaultStyle>
  <resource class="featureType">
    <id>FeatureTypeInfoImpl-19c07171:1971a26b73f:-7eee</id>
  </resource>
  <attribution>
    <logoWidth>0</logoWidth>
    <logoHeight>0</logoHeight>
  </attribution>
  <dateCreated>2025-05-29 03:53:19.298 UTC</dateCreated>
  <dateModified>2025-06-05 08:35:09.100 UTC</dateModified>
</layer>