<GeoServerTileLayer>
  <id>LayerInfoImpl-19c07171:1971a26b73f:-7eeb</id>
  <enabled>true</enabled>
  <inMemoryCached>true</inMemoryCached>
  <name>rubber:bak_rub1_trang_v1_pu</name>
  <mimeFormats>
    <string>image/png</string>
    <string>image/jpeg</string>
  </mimeFormats>
  <gridSubsets>
    <gridSubset>
      <gridSetName>EPSG:4326</gridSetName>
      <extent>
        <coords>
          <double>99.31172180175781</double>
          <double>7.209070205688477</double>
          <double>99.82467651367188</double>
          <double>7.997707843780518</double>
        </coords>
      </extent>
    </gridSubset>
    <gridSubset>
      <gridSetName>EPSG:900913</gridSetName>
      <extent>
        <coords>
          <double>1.1055330300774924E7</double>
          <double>804635.8901111555</double>
          <double>1.1112432158105208E7</double>
          <double>893206.0824540186</double>
        </coords>
      </extent>
    </gridSubset>
  </gridSubsets>
  <metaWidthHeight>
    <int>4</int>
    <int>4</int>
  </metaWidthHeight>
  <expireCache>0</expireCache>
  <expireClients>0</expireClients>
  <parameterFilters>
    <styleParameterFilter>
      <key>STYLES</key>
      <defaultValue></defaultValue>
      <availableStyles class="sorted-set"/>
      <defaultStyle>rubber:rubber_pacel</defaultStyle>
    </styleParameterFilter>
  </parameterFilters>
  <gutter>0</gutter>
  <cacheWarningSkips/>
</GeoServerTileLayer>